medicine/__init__.py
medicine/admin.py
medicine/apps.py
medicine/models.py
medicine/tests.py
medicine/urls.py
medicine/views.py
medicine/backends/__init__.py
medicine/backends/oss_storage_engein.py
medicine/dto/__init__.py
medicine/dto/dtos.py
medicine/dto/params.py
medicine/filters/__init__.py
medicine/filters/completion_filter.py
medicine/migrations/0001_initial.py
medicine/migrations/__init__.py
medicine-0.1.9.dist-info/AUTHORS
medicine-0.1.9.dist-info/METADATA
medicine-0.1.9.dist-info/WHEEL
medicine-0.1.9.dist-info/pbr.json
medicine-0.1.9.dist-info/top_level.txt
medicine-0.1.9.dist-info/RECORD
