Metadata-Version: 2.1
Name: medicine
Version: 0.1.9
Summary: awsome project created by pycman.
Home-page: http://example.com
Author: singein
Author-email: singein@outlook.com
License: MIT
Platform: UNKNOWN
Requires-Dist: DjangoAppCenter (~=0.9.3)
Requires-Dist: oss2 (==2.14.0)
Requires-Dist: mysqlclient (==2.0.3)
Requires-Dist: pypinyin (==0.37.0)
Requires-Dist: django-tabbed-admin (==1.0.4)
Requires-Dist: django-simpleui (==2021.4.1)
Requires-Dist: Pillow (==8.1.2)
Requires-Dist: pbr (~=5.5.1)
Requires-Dist: setuptools (~=54.1.2)
Requires-Dist: six (~=1.15.0)
Requires-Dist: wheel (~=0.36.2)
Requires-Dist: Django (~=3.0.2)
